seosportsinsight-0.2.0.dist-info/METADATA
seosportsinsight-0.2.0.dist-info/WHEEL
seosportsinsight-0.2.0.dist-info/entry_points.txt
seosportsinsight/__init__.py
seosportsinsight/cli.py
seosportsinsight-0.2.0.dist-info/RECORD
